MANIFEST.in
README.rst
bootstrap.py
buildout.cfg
jpl.mcl.site.knowledge.sublime-project
setup.py
docs/HISTORY.txt
docs/INSTALL.txt
docs/LICENSE.txt
docs/new-types.rst
etc/sources.cfg
src/jpl/__init__.py
src/jpl.mcl.site.knowledge.egg-info/PKG-INFO
src/jpl.mcl.site.knowledge.egg-info/SOURCES.txt
src/jpl.mcl.site.knowledge.egg-info/dependency_links.txt
src/jpl.mcl.site.knowledge.egg-info/entry_points.txt
src/jpl.mcl.site.knowledge.egg-info/namespace_packages.txt
src/jpl.mcl.site.knowledge.egg-info/not-zip-safe
src/jpl.mcl.site.knowledge.egg-info/requires.txt
src/jpl.mcl.site.knowledge.egg-info/top_level.txt
src/jpl/mcl/__init__.py
src/jpl/mcl/site/__init__.py
src/jpl/mcl/site/knowledge/README.rst
src/jpl/mcl/site/knowledge/__init__.py
src/jpl/mcl/site/knowledge/_base.py
src/jpl/mcl/site/knowledge/_utils.py
src/jpl/mcl/site/knowledge/configure.zcml
src/jpl/mcl/site/knowledge/degree.py
src/jpl/mcl/site/knowledge/degreefolder.py
src/jpl/mcl/site/knowledge/discipline.py
src/jpl/mcl/site/knowledge/disciplinefolder.py
src/jpl/mcl/site/knowledge/disease.py
src/jpl/mcl/site/knowledge/diseasefolder.py
src/jpl/mcl/site/knowledge/errors.py
src/jpl/mcl/site/knowledge/group.py
src/jpl/mcl/site/knowledge/groupfolder.py
src/jpl/mcl/site/knowledge/institution.py
src/jpl/mcl/site/knowledge/institutionfolder.py
src/jpl/mcl/site/knowledge/interfaces.py
src/jpl/mcl/site/knowledge/organ.py
src/jpl/mcl/site/knowledge/organfolder.py
src/jpl/mcl/site/knowledge/participatingsite.py
src/jpl/mcl/site/knowledge/participatingsitefolder.py
src/jpl/mcl/site/knowledge/person.py
src/jpl/mcl/site/knowledge/personfolder.py
src/jpl/mcl/site/knowledge/protocol.py
src/jpl/mcl/site/knowledge/protocolfolder.py
src/jpl/mcl/site/knowledge/publication.py
src/jpl/mcl/site/knowledge/publicationfolder.py
src/jpl/mcl/site/knowledge/setuphandlers.py
src/jpl/mcl/site/knowledge/siteingestor.py
src/jpl/mcl/site/knowledge/species.py
src/jpl/mcl/site/knowledge/speciesfolder.py
src/jpl/mcl/site/knowledge/specimentype.py
src/jpl/mcl/site/knowledge/specimentypefolder.py
src/jpl/mcl/site/knowledge/testing.py
src/jpl/mcl/site/knowledge/upgrades.py
src/jpl/mcl/site/knowledge/upgrades.zcml
src/jpl/mcl/site/knowledge/browser/__init__.py
src/jpl/mcl/site/knowledge/browser/configure.zcml
src/jpl/mcl/site/knowledge/browser/settings.py
src/jpl/mcl/site/knowledge/degreefolder_templates/view.pt
