Metadata-Version: 2.1
Name: jpl.mcl.site.knowledge
Version: 0.0.7
Summary: Knowledge representation for the MCL site
Home-page: https://github.com/MCLConsortium/jpl.mcl.site.knowledge
Author: Sean Kelly
Author-email: sean.kelly@jpl.nasa.gov
Maintainer: Sean Kelly
Maintainer-email: sean.kelly@jpl.nasa.gov
License: Proprietary
Download-URL: https://github.com/MCLConsortium/jpl.mcl.site.knowledge/archive/0.0.7.zip
Keywords: plone zope knowledge mcl
Platform: UNKNOWN
Classifier: Development Status :: 2 - Pre-Alpha
Classifier: Environment :: Web Environment
Classifier: Framework :: Plone
Classifier: License :: Other/Proprietary License
Classifier: Operating System :: OS Independent
Classifier: Programming Language :: Python
Classifier: Topic :: Internet :: WWW/HTTP
Classifier: Topic :: Software Development :: Libraries :: Python Modules
Provides-Extra: test
